{
  "veins": [
    {
      "block_id": 3,
      "name": "iron",
      "min_y": 5,
      "max_y": 40,
      "threshold": 0.5,
      "frequency": 0.08,
      "vein_size": 8
    },
    {
      "block_id": 53,
      "name": "copper",
      "min_y": 10,
      "max_y": 60,
      "threshold": 0.6,
      "frequency": 0.10,
      "vein_size": 10
    },
    {
      "block_id": 25,
      "name": "tin",
      "min_y": 10,
      "max_y": 50,
      "threshold": 0.7,
      "frequency": 0.12,
      "vein_size": 12
    },
    {
      "block_id": 5,
      "name": "gold",
      "min_y": 5,
      "max_y": 30,
      "threshold": 0.8,
      "frequency": 0.13,
      "vein_size": 6
    },
    {
      "block_id": 87,
      "name": "coal",
      "min_y": 5,
      "max_y": 80,
      "threshold": 0.75,
      "frequency": 0.15,
      "vein_size": 15
    },
    {
      "block_id": 88,
      "name": "redstone",
      "min_y": 5,
      "max_y": 20,
      "threshold": 0.85,
      "frequency": 0.12,
      "vein_size": 5
    },
    {
      "block_id": 89,
      "name": "lapis",
      "min_y": 10,
      "max_y": 30,
      "threshold": 0.88,
      "frequency": 0.11,
      "vein_size": 7
    },
    {
      "block_id": 90,
      "name": "diamond",
      "min_y": 5,
      "max_y": 15,
      "threshold": 0.9,
      "frequency": 0.09,
      "vein_size": 4
    }
  ]
}